postgres_service_pkg/__init__.py
tessco_commons_postgres-1.0.0.dist-info/LICENSE
tessco_commons_postgres-1.0.0.dist-info/METADATA
tessco_commons_postgres-1.0.0.dist-info/WHEEL
tessco_commons_postgres-1.0.0.dist-info/top_level.txt
tessco_commons_postgres-1.0.0.dist-info/RECORD
